patchwork/__init__.py
patchwork/_version.py
patchwork/environment.py
patchwork/files.py
patchwork/info.py
patchwork/transfers.py
patchwork/util.py
patchwork/packages/__init__.py
patchwork-1.0.1.dist-info/DESCRIPTION.rst
patchwork-1.0.1.dist-info/LICENSE.txt
patchwork-1.0.1.dist-info/METADATA
patchwork-1.0.1.dist-info/metadata.json
patchwork-1.0.1.dist-info/RECORD
patchwork-1.0.1.dist-info/top_level.txt
patchwork-1.0.1.dist-info/WHEEL
